setup.cfg
setup.py
lsa/__init__.py
lsa/normalize.py
lsa/schemas.py
lsa/record/__init__.py
lsa/record/base.py
lsa/record/bib.py
lsa/record/froac.py
lsa/record/isi.py
lsa/record/util.py
lsa/scripts/__init__.py
lsa/scripts/dbutil.py
lsa/scripts/model.py
lsa/scripts/populate.py
lsa/scripts/query.py
lsa_program.egg-info/PKG-INFO
lsa_program.egg-info/SOURCES.txt
lsa_program.egg-info/dependency_links.txt
lsa_program.egg-info/entry_points.txt
lsa_program.egg-info/requires.txt
lsa_program.egg-info/top_level.txt
test/test_language_gessing.py
test/test_normalizer.py
test/test_record.py
test/test_scripts.py
test/test_utils.py