Metadata-Version: 1.1
Name: lsa-program
Version: 0.3.0
Summary: A latent semantic search engine implementation
Home-page: https://github.com/odarbelaeze/lsa-program
Author: Oscar David Arbeláez <@odarbelaeze>, German Augusto Osorio
Author-email: odarbelaeze@gmail.com
License: UNKNOWN
Download-URL: https://github.com/odarbelaeze/lsa-program/targall/0.3.0
Keywords: lsa,search,search engine,semantics
Platform: UNKNOWN
